amira/__init__.py
amira/amira.py
amira/data_processor.py
amira/results_uploader.py
amira/s3.py
amira/sqs.py
amira-2.0.3.dist-info/LICENSE.md
amira-2.0.3.dist-info/METADATA
amira-2.0.3.dist-info/WHEEL
amira-2.0.3.dist-info/top_level.txt
amira-2.0.3.dist-info/RECORD
