Metadata-Version: 2.1
Name: amira
Version: 2.0.3
Summary: Automated Malware Incident Response and Analysis
Home-page: https://github.com/Yelp/amira
Author: Yelp Security
Author-email: opensource@yelp.com
License: The MIT License (MIT)
Platform: UNKNOWN
Provides: amira
Requires-Dist: boto3
Requires-Dist: osxcollector-output-filters (>=1.1.1)
Requires-Dist: simplejson
